coconut/__init__.py
coconut_api-0.0.1.dist-info/METADATA
coconut_api-0.0.1.dist-info/WHEEL
coconut_api-0.0.1.dist-info/top_level.txt
coconut_api-0.0.1.dist-info/RECORD
